llama_index/readers/snowflake/__init__.py
llama_index/readers/snowflake/base.py
llama_index_readers_snowflake-0.4.1.dist-info/METADATA
llama_index_readers_snowflake-0.4.1.dist-info/WHEEL
llama_index_readers_snowflake-0.4.1.dist-info/licenses/LICENSE
llama_index_readers_snowflake-0.4.1.dist-info/RECORD
