Metadata-Version: 2.4
Name: llama-index-readers-snowflake
Version: 0.4.1
Summary: llama-index readers snowflake integration
Author-email: Your Name <you@example.com>
Maintainer: godwin3737
License-Expression: MIT
License-File: LICENSE
Keywords: data warehouse,database,snowflake,warehouse
Requires-Python: <4.0,>=3.9
Requires-Dist: llama-index-core<0.15,>=0.13.0
